paddlelabel_ml/__init__.py
paddlelabel_ml/__main__.py
paddlelabel_ml/api.py
paddlelabel_ml/openapi.yml
paddlelabel_ml/util.py
paddlelabel_ml/version
paddlelabel_ml/model/__init__.py
paddlelabel_ml/model/OCR/__init__.py
paddlelabel_ml/model/OCR/info.yaml
paddlelabel_ml/model/OCR/model.py
paddlelabel_ml/model/PPLCNetV2/__init__.py
paddlelabel_ml/model/PPLCNetV2/info.yaml
paddlelabel_ml/model/PPLCNetV2/labels.txt
paddlelabel_ml/model/PPLCNetV2/model.py
paddlelabel_ml/model/PPLCNetV2/operators.py
paddlelabel_ml/model/PPLCNetV2/postprocess.py
paddlelabel_ml/model/PPLCNetV2/ckpt/inference.pdiparams
paddlelabel_ml/model/PPLCNetV2/ckpt/inference.pdiparams.info
paddlelabel_ml/model/PPLCNetV2/ckpt/inference.pdmodel
paddlelabel_ml/model/PicoDet/__init__.py
paddlelabel_ml/model/PicoDet/info.yaml
paddlelabel_ml/model/PicoDet/model.py
paddlelabel_ml/model/PicoDet/postprocess.py
paddlelabel_ml/model/PicoDet/preprocess.py
paddlelabel_ml/model/PicoDet/utils.py
paddlelabel_ml/model/PicoDet/visualize.py
paddlelabel_ml/model/PicoDet/ckpt/infer_cfg.yml
paddlelabel_ml/model/PicoDet/ckpt/model.pdiparams
paddlelabel_ml/model/PicoDet/ckpt/model.pdiparams.info
paddlelabel_ml/model/PicoDet/ckpt/model.pdmodel
paddlelabel_ml/model/base/__init__.py
paddlelabel_ml/model/base/model.py
paddlelabel_ml/model/eiseg/__init__.py
paddlelabel_ml/model/eiseg/info.yaml
paddlelabel_ml/model/eiseg/model.py
paddlelabel_ml/model/eiseg/ckpt/static_hrnet18_ocr64_cocolvis.pdiparams
paddlelabel_ml/model/eiseg/ckpt/static_hrnet18_ocr64_cocolvis.pdmodel
paddlelabel_ml/model/eiseg/inference/__init__.py
paddlelabel_ml/model/eiseg/inference/clicker.py
paddlelabel_ml/model/eiseg/inference/predictor/__init__.py
paddlelabel_ml/model/eiseg/inference/predictor/base.py
paddlelabel_ml/model/eiseg/inference/predictor/ops.py
paddlelabel_ml/model/eiseg/inference/transforms/__init__.py
paddlelabel_ml/model/eiseg/inference/transforms/base.py
paddlelabel_ml/model/eiseg/inference/transforms/crops.py
paddlelabel_ml-1.0.0.dist-info/LICENSE
paddlelabel_ml-1.0.0.dist-info/METADATA
paddlelabel_ml-1.0.0.dist-info/WHEEL
paddlelabel_ml-1.0.0.dist-info/entry_points.txt
paddlelabel_ml-1.0.0.dist-info/top_level.txt
paddlelabel_ml-1.0.0.dist-info/RECORD
