Metadata-Version: 2.1
Name: paddlelabel-ml
Version: 1.0.0
Summary: Web Based Multi Purpose Annotation Tool - ML backend
Home-page: https://github.com/PaddleCV-SIG/PP-Label-ML
Author: PaddleCV-SIG
Author-email: me@linhan.email
License: Apache Software License
Classifier: License :: OSI Approved :: Apache Software License
Classifier: Programming Language :: Python :: 3
Classifier: Programming Language :: Python :: 3.10
License-File: LICENSE
Requires-Dist: flask[async]
Requires-Dist: connexion[swagger-ui]
Requires-Dist: Pillow
Requires-Dist: opencv-python
Requires-Dist: numpy (<=1.23.5)
Requires-Dist: tqdm
Requires-Dist: flask-cors
Requires-Dist: scipy
Requires-Dist: paddleocr
